<?xml version="1.0" encoding="UTF-8" ?>
<!DOCTYPE mapper PUBLIC "-//mybatis.org//DTD Mapper 3.0//EN" "http://mybatis.org/dtd/mybatis-3-mapper.dtd" >
<mapper namespace="com.cht.ddhb.module.sm.dao.SmRoleDAO" >

  <resultMap id="SmRoleResultMap" type="com.cht.ddhb.domain.SmRole" >
    <id column="role_id" property="roleId" jdbcType="VARCHAR" />
    <result column="name" property="name" jdbcType="VARCHAR" />
    <result column="describle" property="describle" jdbcType="VARCHAR" />
    <result column="validity" property="validity" jdbcType="BIT" />
    <result column="oper_id" property="operId" jdbcType="VARCHAR" />
    <result column="oper_time" property="operTime" jdbcType="TIMESTAMP" />
  </resultMap>

  <sql id="SmRole_Column_List" >
    role_id, name, describle, validity, oper_id, oper_time
  </sql>

  <select id="selectByPrimaryKey" resultMap="SmRoleResultMap" parameterType="java.lang.String" >
    select 
    <include refid="SmRole_Column_List" />
    from t_sm_role
    where role_id = #{roleId,jdbcType=VARCHAR}
  </select>

  <delete id="deleteByPrimaryKey" parameterType="java.lang.String" >
    delete from t_sm_role
    where role_id = #{roleId,jdbcType=VARCHAR}
  </delete>

  <insert id="insert" parameterType="com.cht.ddhb.domain.SmRole" >
    insert into t_sm_role (role_id, name, describle, validity, 
      oper_id, oper_time)
    values (uuid(), #{name,jdbcType=VARCHAR}, #{describle,jdbcType=VARCHAR}, ${VALID}, 
      #{operId,jdbcType=VARCHAR}, now())
  </insert>

  <update id="updateByPrimaryKeySelective" parameterType="com.cht.ddhb.domain.SmRole" >
    update t_sm_role
    <set >
      <if test="name != null" >
        NAME = #{name,jdbcType=VARCHAR},
      </if>
      <if test="describle != null" >
        DESCRIBLE = #{describle,jdbcType=VARCHAR},
      </if>
      <if test="validity != null" >
        VALIDITY = #{validity,jdbcType=BIT},
      </if>
      <if test="operId != null" >
        OPER_ID = #{operId,jdbcType=VARCHAR},
      </if>
      <if test="operTime != null" >
        OPER_TIME = now(),
      </if>
    </set>
    where role_id = #{roleId,jdbcType=VARCHAR}
  </update>

  <update id="updateByPrimaryKey" parameterType="com.cht.ddhb.domain.SmRole" >
    update t_sm_role
    set NAME = #{name,jdbcType=VARCHAR},
      DESCRIBLE = #{describle,jdbcType=VARCHAR},
      VALIDITY = #{validity,jdbcType=BIT},
      OPER_ID = #{operId,jdbcType=VARCHAR},
      OPER_TIME = now()
    where role_id = #{roleId,jdbcType=VARCHAR}
  </update>

  <sql id="Where_Condition" >
    <where >
      <if test="name != null and name != ''" >
        NAME = #{name,jdbcType=VARCHAR}
      </if>
      <if test="describle != null and describle != ''" >
        AND DESCRIBLE = #{describle,jdbcType=VARCHAR}
      </if>
      <if test="validity != null" >
        AND VALIDITY = #{validity,jdbcType=BIT}
      </if>
    </where>
  </sql>

  <sql id="Where_Fuzzy_Condition" >
    <where >
      <if test="name != null and name != ''" >
        name = #{name,jdbcType=VARCHAR}
      </if>
      <if test="describle != null and describle != ''" >
        AND describle = #{describle,jdbcType=VARCHAR}
      </if>
      <if test="validity != null" >
        AND validity = #{validity,jdbcType=BIT}
      </if>
      <if test="operId != null and operId != ''" >
        AND oper_id = #{operId,jdbcType=VARCHAR}
      </if>
      <if test="operTime != null" >
        AND oper_time = #{operTime,jdbcType=TIMESTAMP}
      </if>
    </where>
  </sql>

  <select id="queryCount" parameterType="com.cht.ddhb.domain.SmRole" resultType="java.lang.Integer" >
    select count(0) from t_sm_role
    <if test="isFuzzyQuery == false" >
      <include refid="Where_Condition" />
    </if>
    <if test="isFuzzyQuery == true" >
      <include refid="Where_Fuzzy_Condition" />
    </if>
  </select>

  <select id="queryPagedList" parameterType="com.cht.ddhb.domain.SmRole" resultMap="SmRoleResultMap" >
    select 
    <include refid="SmRole_Column_List" />
    from t_sm_role
    <if test="isFuzzyQuery == false" >
      <include refid="Where_Condition" />
    </if>
    <if test="isFuzzyQuery == true" >
      <include refid="Where_Fuzzy_Condition" />
    </if>
    <if test="sort != null" >
      ORDER BY ${sort} ${order}
    </if>
    <if test="sort == null" >
      ORDER BY OPER_TIME DESC
    </if>
  </select>
</mapper>